eb_sqs/__init__.py
eb_sqs/apps.py
eb_sqs/decorators.py
eb_sqs/settings.py
eb_sqs/test_settings.py
eb_sqs/auto_tasks/__init__.py
eb_sqs/auto_tasks/exceptions.py
eb_sqs/auto_tasks/service.py
eb_sqs/aws/__init__.py
eb_sqs/aws/sqs_queue_client.py
eb_sqs/management/__init__.py
eb_sqs/management/commands/__init__.py
eb_sqs/management/commands/healthcheck.py
eb_sqs/management/commands/process_queue.py
eb_sqs/tests/__init__.py
eb_sqs/tests/tests_decorators.py
eb_sqs/tests/auto_tasks/__init__.py
eb_sqs/tests/auto_tasks/tests_auto_tasks.py
eb_sqs/tests/aws/__init__.py
eb_sqs/tests/aws/tests_aws_queue_client.py
eb_sqs/tests/worker/__init__.py
eb_sqs/tests/worker/tests_worker.py
eb_sqs/tests/worker/tests_worker_task.py
eb_sqs/worker/__init__.py
eb_sqs/worker/commons.py
eb_sqs/worker/queue_client.py
eb_sqs/worker/service.py
eb_sqs/worker/sqs_worker_factory.py
eb_sqs/worker/worker.py
eb_sqs/worker/worker_exceptions.py
eb_sqs/worker/worker_factory.py
eb_sqs/worker/worker_task.py
django_eb_sqs-1.44.dist-info/LICENSE
django_eb_sqs-1.44.dist-info/METADATA
django_eb_sqs-1.44.dist-info/WHEEL
django_eb_sqs-1.44.dist-info/top_level.txt
django_eb_sqs-1.44.dist-info/RECORD
