Metadata-Version: 2.1
Name: django-eb-sqs
Version: 1.44
Summary: A simple task manager for AWS SQS
Home-page: https://github.com/cuda-networks/django-eb-sqs
License: UNKNOWN
Platform: UNKNOWN
Classifier: Intended Audience :: Developers
Classifier: Programming Language :: Python :: 3.7
Classifier: Programming Language :: Python :: 2.7
Classifier: Topic :: Software Development
Classifier: License :: OSI Approved :: MIT License
Classifier: Operating System :: OS Independent
Classifier: Framework :: Django
Requires-Dist: boto3 (>=1.9.86)
Requires-Dist: Django (>=1.10.6)
Requires-Dist: requests (>=2.10.0)
